{
  "posts": [
    {
      "id": 1,
      "name": "Keyboard",
      "amount": "500",
      "category": "Education"
    },
    {
      "name": "Burger",
      "amount": "800",
      "category": "Food",
      "id": 2
    },
    {
      "name": "Movies",
      "amount": "1500",
      "category": "Entertainment",
      "id": 3
    },
    {
      "name": "Train Tickets",
      "amount": "1500",
      "category": "Travel",
      "id": 4
    },
    {
      "id": 5,
      "name": "Recharge",
      "amount": "666",
      "category": "Bills"
    }
  ],
  "comments": [],
  "profile": {
    "name": "typicode"
  }
}